iolite_client/__init__.py
iolite_client/client.py
iolite_client/entity.py
iolite_client/entity_factory.py
iolite_client/exceptions.py
iolite_client/heating_scheduler.py
iolite_client/oauth_handler.py
iolite_client/request_handler.py
iolite_client-0.7.3.dist-info/LICENSE.md
iolite_client-0.7.3.dist-info/WHEEL
iolite_client-0.7.3.dist-info/METADATA
iolite_client-0.7.3.dist-info/RECORD
