Metadata-Version: 2.1
Name: iolite-client
Version: 0.7.3
Summary: API client for interacting with IOLite's remote API
Home-page: https://github.com/inverse/python-iolite-client
License: MIT
Author: Malachi Soord
Author-email: me@malachisoord.com
Requires-Python: >=3.8,<4.0
Classifier: License :: OSI Approved :: MIT License
Classifier: Programming Language :: Python :: 3
Classifier: Programming Language :: Python :: 3.8
Classifier: Programming Language :: Python :: 3.9
Classifier: Programming Language :: Python :: 3.10
Classifier: Programming Language :: Python :: 3.11
Provides-Extra: dev
Requires-Dist: aiohttp (>=3.7.4,<4.0.0)
Requires-Dist: requests
Requires-Dist: single-source (>=0.2,<0.4)
Requires-Dist: websockets
Project-URL: Repository, https://github.com/inverse/python-iolite-client
